checkerpy/__init__.py
checkerpy/exceptions.py
checkerpy/decorators/__init__.py
checkerpy/decorators/bounded.py
checkerpy/decorators/boundsparser.py
checkerpy/decorators/decorator.py
checkerpy/decorators/mixin.py
checkerpy/decorators/mixins.py
checkerpy/decorators/typed.py
checkerpy/decorators/typeparser.py
checkerpy/functional/__init__.py
checkerpy/functional/composition.py
checkerpy/functional/mixins.py
checkerpy/types/__init__.py
checkerpy/types/all/__init__.py
checkerpy/types/all/all.py
checkerpy/types/all/base.py
checkerpy/types/all/compound.py
checkerpy/types/all/docstring.py
checkerpy/types/all/typeddict.py
checkerpy/types/all/typedtuple.py
checkerpy/types/numpy/__init__.py
checkerpy/types/numpy/base.py
checkerpy/types/numpy/compound.py
checkerpy/types/numpy/docstring.py
checkerpy/types/numpy/justdtype.py
checkerpy/types/numpy/justndarray.py
checkerpy/types/one/__init__.py
checkerpy/types/one/base.py
checkerpy/types/one/compound.py
checkerpy/types/one/docstring.py
checkerpy/types/one/just.py
checkerpy/types/weak/__init__.py
checkerpy/types/weak/docstring.py
checkerpy/types/weak/like.py
checkerpy/validators/__init__.py
checkerpy/validators/all/__init__.py
checkerpy/validators/all/allhave.py
checkerpy/validators/all/alllen.py
checkerpy/validators/all/alllimited.py
checkerpy/validators/all/allnonempty.py
checkerpy/validators/all/limitedtuple.py
checkerpy/validators/all/registrars.py
checkerpy/validators/numpy/__init__.py
checkerpy/validators/numpy/justndim.py
checkerpy/validators/numpy/justshape.py
checkerpy/validators/numpy/justsize.py
checkerpy/validators/numpy/registrar.py
checkerpy/validators/one/__init__.py
checkerpy/validators/one/call.py
checkerpy/validators/one/contains.py
checkerpy/validators/one/has.py
checkerpy/validators/one/identifier.py
checkerpy/validators/one/justcall.py
checkerpy/validators/one/justlen.py
checkerpy/validators/one/limited.py
checkerpy/validators/one/nonempty.py
checkerpy-0.9.8.dist-info/DESCRIPTION.rst
checkerpy-0.9.8.dist-info/METADATA
checkerpy-0.9.8.dist-info/RECORD
checkerpy-0.9.8.dist-info/WHEEL
checkerpy-0.9.8.dist-info/metadata.json
checkerpy-0.9.8.dist-info/top_level.txt
