Metadata-Version: 2.0
Name: checkerpy
Version: 0.9.8
Summary: Type and value checkers both as callables and decorators
Home-page: https://github.com/yedivanseven/CheckerPy
Author: Georg Heimel
Author-email: georg@muckisnspirit.com
License: MIT
Download-URL: https://pypi.python.org/pypi/checkerpy
Keywords: validation
Platform: UNKNOWN
Classifier: Development Status :: 4 - Beta
Classifier: Intended Audience :: Developers
Classifier: License :: OSI Approved :: MIT License
Classifier: Natural Language :: English
Classifier: Operating System :: OS Independent
Classifier: Programming Language :: Python :: 3 :: Only
Classifier: Topic :: Software Development
Requires-Python: >=3.6
